{
  "keyword": "best esim for thailand",
  "query_id": "6e2016f505a04e47",
  "basic_terms": [
    "esim",
    "thailand",
    "sim",
    "sim card",
    "best esim",
    "esim for thailand",
    "data plan",
    "thailand esim",
    "esims",
    "unlimited data",
    "esim plan",
    "5g",
    "ais",
    "mobile data",
    "roam",
    "stay connected",
    "physical sim card",
    "prepay",
    "hotspot",
    "physical sim"
  ],
  "basic_terms_with_ranges": [
    {
      "term": "esim",
      "range": "8-51x"
    },
    {
      "term": "thailand",
      "range": "2-32x"
    },
    {
      "term": "sim",
      "range": "3-15x"
    },
    {
      "term": "sim card",
      "range": "1-6x"
    },
    {
      "term": "best esim",
      "range": "1-3x"
    },
    {
      "term": "esim for thailand",
      "range": "1-2x"
    },
    {
      "term": "data plan",
      "range": "1-8x"
    },
    {
      "term": "thailand esim",
      "range": "1-3x"
    },
    {
      "term": "esims",
      "range": "1-8x"
    },
    {
      "term": "unlimited data",
      "range": "1-4x"
    },
    {
      "term": "esim plan",
      "range": "1-3x"
    },
    {
      "term": "5g",
      "range": "1-5x"
    },
    {
      "term": "ais",
      "range": "1-3x"
    },
    {
      "term": "mobile data",
      "range": "1-2x"
    },
    {
      "term": "roam",
      "range": "1-7x"
    },
    {
      "term": "stay connected",
      "range": "1-3x"
    },
    {
      "term": "physical sim card",
      "range": "1-2x"
    },
    {
      "term": "prepay",
      "range": "1-3x"
    },
    {
      "term": "hotspot",
      "range": "1-2x"
    },
    {
      "term": "physical sim",
      "range": "1-2x"
    }
  ],
  "extended_terms": [
    "best esim for thailand",
    "esim provider",
    "esim thailand",
    "travel esim",
    "thailand travel",
    "data usage",
    "data roaming",
    "best thailand esim",
    "esim data",
    "use an esim",
    "15 days",
    "unlimited data plan",
    "esim option",
    "esims for thailand",
    "use in thailand",
    "trip to thailand",
    "high-speed data",
    "install the esim",
    "local network",
    "data package",
    "unlimited plans",
    "data options",
    "esim data plan",
    "local sim",
    "run out of data",
    "plan for thailand",
    "across thailand",
    "get connected",
    "esim in thailand",
    "esim service",
    "jetpac esim",
    "much data",
    "amount of data",
    "connected in thailand",
    "activate your esim",
    "mobile network",
    "embedded sim",
    "install your esim",
    "prepaid esim",
    "global esim",
    "travel esims",
    "thailand plans",
    "buy an esim",
    "best network",
    "offers unlimited data",
    "offers unlimited",
    "best esims",
    "esim plans for thailand",
    "travel needs",
    "get an esim for thailand",
    "local sim cards",
    "data in thailand",
    "arrive in thailand",
    "esim online",
    "esim with unlimited data",
    "new esim",
    "esim technology",
    "cellular data",
    "esim package",
    "thailand esim plans",
    "local phone number",
    "5g data",
    "data packs",
    "esim for data",
    "use your data",
    "prepaid data plans",
    "option in thailand",
    "install an esim",
    "reliable esim",
    "heading to thailand",
    "esim brands",
    "gb of high-speed data",
    "esim providers offer",
    "data roaming charges",
    "add data plan",
    "buy the best esim",
    "best for thailand",
    "including thailand",
    "prepaid esim plans",
    "using the esim"
  ],
  "extended_terms_with_ranges": [
    {
      "term": "best esim for thailand",
      "range": "1x"
    },
    {
      "term": "esim provider",
      "range": "1x"
    },
    {
      "term": "esim thailand",
      "range": "1x"
    },
    {
      "term": "travel esim",
      "range": "1x"
    },
    {
      "term": "thailand travel",
      "range": "1x"
    },
    {
      "term": "data usage",
      "range": "1x"
    },
    {
      "term": "data roaming",
      "range": "1x"
    },
    {
      "term": "best thailand esim",
      "range": "1x"
    },
    {
      "term": "esim data",
      "range": "1x"
    },
    {
      "term": "use an esim",
      "range": "1x"
    },
    {
      "term": "15 days",
      "range": "1x"
    },
    {
      "term": "unlimited data plan",
      "range": "1x"
    },
    {
      "term": "esim option",
      "range": "1x"
    },
    {
      "term": "esims for thailand",
      "range": "1x"
    },
    {
      "term": "use in thailand",
      "range": "1x"
    },
    {
      "term": "trip to thailand",
      "range": "1x"
    },
    {
      "term": "high-speed data",
      "range": "1x"
    },
    {
      "term": "install the esim",
      "range": "1x"
    },
    {
      "term": "local network",
      "range": "1x"
    },
    {
      "term": "data package",
      "range": "1x"
    },
    {
      "term": "unlimited plans",
      "range": "1x"
    },
    {
      "term": "data options",
      "range": "1x"
    },
    {
      "term": "esim data plan",
      "range": "1x"
    },
    {
      "term": "local sim",
      "range": "1x"
    },
    {
      "term": "run out of data",
      "range": "1x"
    },
    {
      "term": "plan for thailand",
      "range": "1x"
    },
    {
      "term": "across thailand",
      "range": "1x"
    },
    {
      "term": "get connected",
      "range": "1x"
    },
    {
      "term": "esim in thailand",
      "range": "1x"
    },
    {
      "term": "esim service",
      "range": "1x"
    },
    {
      "term": "jetpac esim",
      "range": "1x"
    },
    {
      "term": "much data",
      "range": "1x"
    },
    {
      "term": "amount of data",
      "range": "1x"
    },
    {
      "term": "connected in thailand",
      "range": "1x"
    },
    {
      "term": "activate your esim",
      "range": "1x"
    },
    {
      "term": "mobile network",
      "range": "1x"
    },
    {
      "term": "embedded sim",
      "range": "1x"
    },
    {
      "term": "install your esim",
      "range": "1x"
    },
    {
      "term": "prepaid esim",
      "range": "1x"
    },
    {
      "term": "global esim",
      "range": "1x"
    },
    {
      "term": "travel esims",
      "range": "1x"
    },
    {
      "term": "thailand plans",
      "range": "1x"
    },
    {
      "term": "buy an esim",
      "range": "1x"
    },
    {
      "term": "best network",
      "range": "1x"
    },
    {
      "term": "offers unlimited data",
      "range": "1x"
    },
    {
      "term": "offers unlimited",
      "range": "1x"
    },
    {
      "term": "best esims",
      "range": "1x"
    },
    {
      "term": "esim plans for thailand",
      "range": "1x"
    },
    {
      "term": "travel needs",
      "range": "1x"
    },
    {
      "term": "get an esim for thailand",
      "range": "1x"
    },
    {
      "term": "local sim cards",
      "range": "1x"
    },
    {
      "term": "data in thailand",
      "range": "1x"
    },
    {
      "term": "arrive in thailand",
      "range": "1x"
    },
    {
      "term": "esim online",
      "range": "1x"
    },
    {
      "term": "esim with unlimited data",
      "range": "1x"
    },
    {
      "term": "new esim",
      "range": "1x"
    },
    {
      "term": "esim technology",
      "range": "1x"
    },
    {
      "term": "cellular data",
      "range": "1x"
    },
    {
      "term": "esim package",
      "range": "1x"
    },
    {
      "term": "thailand esim plans",
      "range": "1x"
    },
    {
      "term": "local phone number",
      "range": "1x"
    },
    {
      "term": "5g data",
      "range": "1x"
    },
    {
      "term": "data packs",
      "range": "1x"
    },
    {
      "term": "esim for data",
      "range": "1x"
    },
    {
      "term": "use your data",
      "range": "1x"
    },
    {
      "term": "prepaid data plans",
      "range": "1x"
    },
    {
      "term": "option in thailand",
      "range": "1x"
    },
    {
      "term": "install an esim",
      "range": "1x"
    },
    {
      "term": "reliable esim",
      "range": "1x"
    },
    {
      "term": "heading to thailand",
      "range": "1x"
    },
    {
      "term": "esim brands",
      "range": "1x"
    },
    {
      "term": "gb of high-speed data",
      "range": "1x"
    },
    {
      "term": "esim providers offer",
      "range": "1x"
    },
    {
      "term": "data roaming charges",
      "range": "1x"
    },
    {
      "term": "add data plan",
      "range": "1x"
    },
    {
      "term": "buy the best esim",
      "range": "1x"
    },
    {
      "term": "best for thailand",
      "range": "1x"
    },
    {
      "term": "including thailand",
      "range": "1x"
    },
    {
      "term": "prepaid esim plans",
      "range": "1x"
    },
    {
      "term": "using the esim",
      "range": "1x"
    }
  ],
  "entities": [
    "ESIM",
    "SIM card",
    "Thailand",
    "Wi-Fi",
    "Data",
    "Airalo",
    "Google Maps",
    "Mobile app",
    "Android (operating system)",
    "Wi-Fi hotspot",
    "Bangkok",
    "Internet",
    "Asia",
    "Google",
    "Advanced Info Service",
    "Tethering",
    "Internet access",
    "Ubigi",
    "Holafly",
    "Roaming",
    "Chiang Mai",
    "Pricing",
    "Grab Holdings",
    "Phuket province",
    "Cellular network",
    "5G",
    "DTAC",
    "Phi Phi Islands",
    "Digital nomad",
    "Airport",
    "Nomad",
    "Boat",
    "Holiday"
  ],
  "paa": [
    {
      "q": "Which SIM card is best for tourists in Thailand?"
    },
    {
      "q": "Is Airalo good in Thailand?"
    },
    {
      "q": "Is there a better eSIM than Airalo?"
    },
    {
      "q": "What is the most trusted eSIM?"
    }
  ],
  "questions": []
}
